{
    "沸か": 12,
    "加え": 60,
    "入れ": 52,
    "分ゆで": 4,
    "取り出": 12,
    "さら": 4,
    "抜": 4,
    "絞": 20,
    "切": 60,
    "盛": 16,
    "作": 4,
    "香ばし": 4,
    "からいり": 4,
    "すり混ぜ": 8,
    "する": 12,
    "混ぜ": 32,
    "かけ": 16,
    "切り干し": 8,
    "洗": 4,
    "分": 4,
    "つけ": 16,
    "もど": 4,
    "長": 4,
    "摘み": 4,
    "ゆで": 8,
    "と": 4,
    "さま": 8,
    "上げ": 8,
    "き": 16,
    "取": 4,
    "熱": 12,
    "炒め": 12,
    "すりおろし": 8,
    "止め": 4,
    "2": 12,
    "あえ": 8,
    "1": 4,
    "のせ": 8,
    "混ぜ合わせ": 12,
    "さ": 4,
    "のば": 4,
    "し": 24,
    "弱め": 4,
    "切り分け": 4,
    "落と": 8,
    "削り取": 4,
    "出": 4,
    "水洗い": 8,
    "拭": 8,
    "寝かせ": 4,
    "動か": 4,
    "はず": 8,
    "返": 8,
    "そぎ取": 4,
    "ふ": 8,
    "包": 4,
    "6": 4,
    "溶": 8,
    "からめ": 8,
    "まぶしつけ": 4,
    "中温": 4,
    "沈": 4,
    "浮き上が": 4,
    "揚げ": 4,
    "1人": 4,
    "取り除": 8,
    "む": 4,
    "加熱": 4,
    "ほぐ": 4,
    "まぶ": 4,
    "焼": 4,
    "戻し入れ": 4,
    "回し入れ": 4
}